kommand/__init__.py
kommand/__main__.py
kommand/ansi_text.py
kommand-1.0.dist-info/LICENSE
kommand-1.0.dist-info/METADATA
kommand-1.0.dist-info/WHEEL
kommand-1.0.dist-info/top_level.txt
kommand-1.0.dist-info/RECORD
