Metadata-Version: 2.1
Name: kommand
Version: 1.0
Summary: This is your kommand, CLI interactive with python
Home-page: https://github.com/kzulfazriawan/kommand
Author: kzulfazriawan
Author-email: kzulfazriawan@gmail.com
License: UNKNOWN
Platform: UNKNOWN
Classifier: Programming Language :: Python :: 3
Classifier: License :: OSI Approved :: MIT License
Classifier: Operating System :: OS Independent
Requires-Python: >=3.6
License-File: LICENSE
